pycares_owl_corp_temp_fork-4.2.2.dist-info/LICENSE
pycares_owl_corp_temp_fork-4.2.2.dist-info/top_level.txt
pycares_owl_corp_temp_fork-4.2.2.dist-info/WHEEL
pycares_owl_corp_temp_fork-4.2.2.dist-info/RECORD
pycares_owl_corp_temp_fork-4.2.2.dist-info/METADATA
pycares/utils.py
pycares/_cares.cpython-37m-x86_64-linux-gnu.so
pycares/_version.py
pycares/errno.py
pycares/__main__.py
pycares/__init__.py
