Metadata-Version: 2.1
Name: pycares-owl-corp-temp-fork
Version: 4.2.2
Summary: Python interface for c-ares
Home-page: http://github.com/owl-corp/pycares
Author: Owl Corp
License: MIT
Platform: POSIX
Platform: Microsoft Windows
Classifier: Development Status :: 5 - Production/Stable
Classifier: Intended Audience :: Developers
Classifier: License :: OSI Approved :: MIT License
Classifier: Operating System :: POSIX
Classifier: Operating System :: Microsoft :: Windows
Classifier: Programming Language :: Python
Classifier: Programming Language :: Python :: 3
Classifier: Programming Language :: Python :: 3.6
Classifier: Programming Language :: Python :: 3.7
Classifier: Programming Language :: Python :: 3.8
Classifier: Programming Language :: Python :: 3.9
Classifier: Programming Language :: Python :: 3.10
Classifier: Programming Language :: Python :: Implementation :: CPython
Classifier: Programming Language :: Python :: Implementation :: PyPy
License-File: LICENSE
Requires-Dist: cffi (>=1.5.0)
Provides-Extra: idna
Requires-Dist: idna (>=2.1) ; extra == 'idna'
